LICENSE
MANIFEST.in
README.txt
setup.py
atomisator/__init__.py
atomisator.db.egg-info/PKG-INFO
atomisator.db.egg-info/SOURCES.txt
atomisator.db.egg-info/dependency_links.txt
atomisator.db.egg-info/entry_points.txt
atomisator.db.egg-info/namespace_packages.txt
atomisator.db.egg-info/not-zip-safe
atomisator.db.egg-info/requires.txt
atomisator.db.egg-info/top_level.txt
atomisator/db/__init__.py
atomisator/db/core.py
atomisator/db/mappers.py
atomisator/db/session.py
atomisator/db/docs/README.txt
atomisator/db/docs/mappers.txt
atomisator/db/tests/__init__.py
atomisator/db/tests/test_docs.py
atomisator/db/tests/test_updated.py