Metadata-Version: 1.0
Name: atomisator.db
Version: 0.3.2
Summary: Expert Python Programming - Manages the Atomisator storage.
Home-page: http://atomisator.ziade.org
Author: Tarek Ziade
Author-email: tarek@ziade.org
License: GPL
Keywords: atomisator
Platform: UNKNOWN
Classifier: Programming Language :: Python
Classifier: Topic :: Software Development :: Libraries :: Python Modules
